nonebot/adapters/qqguild/__init__.py
nonebot/adapters/qqguild/adapter.py
nonebot/adapters/qqguild/api/__init__.py
nonebot/adapters/qqguild/api/client.py
nonebot/adapters/qqguild/api/handle.py
nonebot/adapters/qqguild/api/model.py
nonebot/adapters/qqguild/api/request.py
nonebot/adapters/qqguild/api/utils.py
nonebot/adapters/qqguild/bot.py
nonebot/adapters/qqguild/config.py
nonebot/adapters/qqguild/event.py
nonebot/adapters/qqguild/exception.py
nonebot/adapters/qqguild/message.py
nonebot/adapters/qqguild/payload.py
nonebot/adapters/qqguild/permission.py
nonebot/adapters/qqguild/store.py
nonebot/adapters/qqguild/transformer.py
nonebot/adapters/qqguild/utils.py
nonebot_adapter_qqguild-0.4.0.dist-info/METADATA
nonebot_adapter_qqguild-0.4.0.dist-info/WHEEL
nonebot_adapter_qqguild-0.4.0.dist-info/RECORD
