Metadata-Version: 2.1
Name: nonebot-adapter-qqguild
Version: 0.4.0
Summary: QQ Guild adapter for nonebot2
Home-page: https://github.com/nonebot/adapter-qq/tree/master/packages/nonebot-adapter-qqguild
License: MIT
Keywords: bot,qq,qqbot,qqguild
Author: yanyongyu
Author-email: yyy@nonebot.dev
Requires-Python: >=3.8,<4.0
Classifier: Development Status :: 5 - Production/Stable
Classifier: Framework :: Robot Framework
Classifier: Framework :: Robot Framework :: Library
Classifier: License :: OSI Approved :: MIT License
Classifier: Operating System :: OS Independent
Classifier: Programming Language :: Python :: 3
Classifier: Programming Language :: Python :: 3.8
Classifier: Programming Language :: Python :: 3.9
Classifier: Programming Language :: Python :: 3.10
Classifier: Programming Language :: Python :: 3.11
Requires-Dist: nonebot2 (>=2.1.0,<3.0.0)
Requires-Dist: pydantic (>=1.9.0,<2.0.0)
Requires-Dist: typing-extensions (>=4.4.0,<5.0.0)
Project-URL: Documentation, https://github.com/nonebot/adapter-qq#readme
Project-URL: Repository, https://github.com/nonebot/adapter-qq
